publicsuffixlist/__init__.py
publicsuffixlist/compat.py
publicsuffixlist/public_suffix_list.dat
publicsuffixlist/test.py
publicsuffixlist/test_psl.txt
publicsuffixlist/update.py
publicsuffixlist-1.0.2.20260131.dist-info/licenses/LICENSE
publicsuffixlist-1.0.2.20260131.dist-info/METADATA
publicsuffixlist-1.0.2.20260131.dist-info/WHEEL
publicsuffixlist-1.0.2.20260131.dist-info/entry_points.txt
publicsuffixlist-1.0.2.20260131.dist-info/top_level.txt
publicsuffixlist-1.0.2.20260131.dist-info/RECORD
