Metadata-Version: 2.4
Name: publicsuffixlist
Version: 1.0.2.20260131
Summary: publicsuffixlist implement
Home-page: https://github.com/ko-zu/psl
Author: ko-zu
Author-email: causeless@gmail.com
License: MPL-2.0
Classifier: Development Status :: 5 - Production/Stable
Classifier: License :: OSI Approved :: Mozilla Public License 2.0 (MPL 2.0)
Classifier: Topic :: Internet :: Name Service (DNS)
Classifier: Topic :: Text Processing :: Filters
Classifier: Operating System :: OS Independent
Requires-Python: >=3.5
License-File: LICENSE
Provides-Extra: update
Requires-Dist: requests; extra == "update"
Provides-Extra: readme
Requires-Dist: pandoc; extra == "readme"
Dynamic: author
Dynamic: author-email
Dynamic: classifier
Dynamic: description
Dynamic: description-content-type
Dynamic: home-page
Dynamic: license
Dynamic: license-file
Dynamic: provides-extra
Dynamic: requires-python
Dynamic: summary
